boilerio/__init__.py
boilerio/config.py
boilerio/model_BACKUP_8250.py
boilerio/model_BASE_8250.py
boilerio/model_LOCAL_8250.py
boilerio/model_REMOTE_8250.py
boilerio/monitor.py
boilerio/pid.py
boilerio/pwm.py
boilerio/scheduler.py
boilerio/tempsensor.py
boilerio/thermostat.py
boilerio/update_sensor.py
boilerio/weather.py
boilerio/zones.py
boilerio/schedulerweb/__init__.py
boilerio/schedulerweb/app.py
boilerio/schedulerweb/auth.py
boilerio/schedulerweb/google_token.py
boilerio/schedulerweb/model.py
boilerio/schedulerweb/sensors.py
boilerio/schedulerweb/util.py
boilerio/schedulerweb/wsgi.py
boilerio/schedulerweb/zones.py
boilerio/schedulerweb/tests/__init__.py
boilerio/schedulerweb/tests/test_app.py
boilerio/schedulerweb/tests/test_auth.py
boilerio/schedulerweb/tests/test_google_token.py
boilerio/schedulerweb/tests/test_schedulerweb.py
boilerio/tests/__init__.py
boilerio/tests/test_monitor.py
boilerio/tests/test_pwm.py
boilerio/tests/test_scheduler.py
boilerio/tests/test_tempsensor.py
boilerio/tests/test_thermostat.py
boilerio/tests/test_weather.py
boilerio/tests/test_zones.py
boilerio-0.0.5.data/scripts/boiler_to_mqtt
boilerio-0.0.5.data/scripts/boilersim
boilerio-0.0.5.dist-info/LICENSE
boilerio-0.0.5.dist-info/METADATA
boilerio-0.0.5.dist-info/WHEEL
boilerio-0.0.5.dist-info/entry_points.txt
boilerio-0.0.5.dist-info/top_level.txt
boilerio-0.0.5.dist-info/RECORD
