Metadata-Version: 2.1
Name: boilerio
Version: 0.0.5
Summary: A software thermostat and heating control system
Home-page: https://github.com/adpeace/boilerio.git
Author: Andy Peace
Author-email: andrew.peace@gmail.com
License: MIT
Platform: UNKNOWN
Classifier: Development Status :: 2 - Pre-Alpha
Classifier: License :: OSI Approved :: MIT License
License-File: LICENSE
Requires-Dist: Flask
Requires-Dist: requests
Requires-Dist: psycopg2-binary
Requires-Dist: paho-mqtt
Requires-Dist: flask-restx
Requires-Dist: pyserial
Requires-Dist: flask-login
Requires-Dist: basicauth
Requires-Dist: cachecontrol
Requires-Dist: google-auth-oauthlib
